srg/__init__.py
srg/__main__.py
srg/_menu.py
srg-0.0.1.dist-info/METADATA
srg-0.0.1.dist-info/WHEEL
srg-0.0.1.dist-info/entry_points.txt
srg-0.0.1.dist-info/top_level.txt
srg-0.0.1.dist-info/RECORD
