Metadata-Version: 2.1
Name: srg
Version: 0.0.1
Author-email: srg <srg.code@pm.me>
License: Apache License, Version 2.0
Project-URL: Homepage, https://github.com/codesrg/srg
Project-URL: Bug Tracker, https://github.com/codesrg/srg/issues
Keywords: srg
Classifier: Programming Language :: Python :: 3
Classifier: License :: OSI Approved :: Apache Software License
Classifier: Operating System :: OS Independent
Requires-Python: >=3.6
Requires-Dist: srutil
Requires-Dist: sipher
Requires-Dist: ioutil
Requires-Dist: browseon
Requires-Dist: savescreen
Requires-Dist: zenpass
Requires-Dist: local
